engin/__init__.py
engin/_assembler.py
engin/_block.py
engin/_cli/__init__.py
engin/_cli/_check.py
engin/_cli/_common.py
engin/_cli/_graph.html
engin/_cli/_graph.py
engin/_cli/_inspect.py
engin/_dependency.py
engin/_engin.py
engin/_graph.py
engin/_introspect.py
engin/_lifecycle.py
engin/_option.py
engin/_supervisor.py
engin/_type_utils.py
engin/exceptions.py
engin/extensions/__init__.py
engin/extensions/asgi.py
engin/extensions/fastapi.py
engin/py.typed
engin-0.3.0.dist-info/WHEEL
engin-0.3.0.dist-info/entry_points.txt
engin-0.3.0.dist-info/METADATA
engin-0.3.0.dist-info/RECORD
