Metadata-Version: 2.4
Name: engin
Version: 0.3.0
Summary: A dependency-injection powered application framework
Keywords: Dependency Injection,Application Framework
License-Expression: MIT
Requires-Dist: anyio>=4
Requires-Dist: exceptiongroup>=1
Requires-Dist: typing-extensions>=4
Requires-Dist: typer>=0.15 ; extra == 'cli'
Requires-Dist: tomli>=2.0 ; python_full_version < '3.11' and extra == 'cli'
Requires-Python: >=3.10
Project-URL: Changelog, https://github.com/invokermain/engin/blob/main/CHANGELOG.md
Project-URL: Documentation, https://engin.readthedocs.io/en/latest/
Project-URL: Homepage, https://github.com/invokermain/engin
Project-URL: Repository, https://github.com/invokermain/engin.git
Provides-Extra: cli
